mahdi/__init__.py
mahdi/cli.py
mahdi_url_shortener-0.1.2.dist-info/licenses/LICENSE
mahdi_url_shortener-0.1.2.dist-info/METADATA
mahdi_url_shortener-0.1.2.dist-info/WHEEL
mahdi_url_shortener-0.1.2.dist-info/entry_points.txt
mahdi_url_shortener-0.1.2.dist-info/top_level.txt
mahdi_url_shortener-0.1.2.dist-info/RECORD
