Metadata-Version: 2.4
Name: mahdi-url-shortener
Version: 0.1.2
Summary: A simple Python package to shorten URLs via TinyURL with CLI support.
Home-page: https://github.com/oxl_mahdi/mahdi-url-shortener
Author: oxl_mahdi
Author-email: mhasan37608@gmail.com
License: MIT
Project-URL: Bug Tracker, https://github.com/oxl_mahdi/mahdi-url-shortener/issues
Project-URL: Source, https://github.com/oxl_mahdi/mahdi-url-shortener
Classifier: Programming Language :: Python :: 3
Classifier: Programming Language :: Python :: 3.7
Classifier: Programming Language :: Python :: 3.8
Classifier: Programming Language :: Python :: 3.9
Classifier: Programming Language :: Python :: 3.10
Classifier: License :: OSI Approved :: MIT License
Classifier: Operating System :: OS Independent
Classifier: Topic :: Utilities
Classifier: Environment :: Console
Requires-Python: >=3.7
License-File: LICENSE
Requires-Dist: pyshorteners>=1.0.1
Dynamic: author
Dynamic: author-email
Dynamic: classifier
Dynamic: description
Dynamic: description-content-type
Dynamic: home-page
Dynamic: license
Dynamic: license-file
Dynamic: project-url
Dynamic: requires-dist
Dynamic: requires-python
Dynamic: summary
